keepomize/__init__.py
keepomize/cli.py
keepomize/core.py
keepomize-0.1.2.dist-info/licenses/LICENSE
keepomize-0.1.2.dist-info/METADATA
keepomize-0.1.2.dist-info/WHEEL
keepomize-0.1.2.dist-info/entry_points.txt
keepomize-0.1.2.dist-info/top_level.txt
keepomize-0.1.2.dist-info/RECORD
