Metadata-Version: 2.4
Name: keepomize
Version: 0.1.2
Summary: A filter for Kubernetes manifests that resolves Keeper URIs in Secret resources using ksm
Author-email: Nathan Stien <nathanism@gmail.com>
Maintainer-email: Nathan Stien <nathanism@gmail.com>
License-Expression: MIT
Project-URL: Homepage, https://github.com/nathanic/keepomize
Project-URL: Bug Tracker, https://github.com/nathanic/keepomize/issues
Project-URL: Repository, https://github.com/nathanic/keepomize
Project-URL: Documentation, https://github.com/nathanic/keepomize#readme
Keywords: kubernetes,secrets,keeper,kustomize
Classifier: Development Status :: 4 - Beta
Classifier: Environment :: Console
Classifier: Intended Audience :: Developers
Classifier: Intended Audience :: System Administrators
Classifier: Operating System :: OS Independent
Classifier: Programming Language :: Python :: 3
Classifier: Programming Language :: Python :: 3.8
Classifier: Programming Language :: Python :: 3.9
Classifier: Programming Language :: Python :: 3.10
Classifier: Programming Language :: Python :: 3.11
Classifier: Programming Language :: Python :: 3.12
Classifier: Topic :: System :: Systems Administration
Classifier: Topic :: Software Development :: Libraries :: Python Modules
Requires-Python: >=3.8
License-File: LICENSE
Requires-Dist: ruamel.yaml>=0.17
Dynamic: license-file
